Workbook

Sheet README
A1: Mirra stress test - synthetic business template
A2: One workbook = one business shape. The generator script reads it, writes the localStorage seed, and an independent script computes the expected values.
A4: HOW TO FILL IT IN
A5: Yellow cells, blue text | B5: Your inputs. Change these.
A6: Grey cells | B6: Formulas or checks. Do not type over them.
A7: Yellow cells, blue text | B7: Shows the expected format. The generator skips any row whose Ref is EXAMPLE.
A8: Blue text on white | B8: Fixed values copied from the app's defaults. Change only if the business differs.
A10: CONVENTIONS
A11: Percent fields | B11: Enter whole numbers (85 = 85%), not fractions. This matches how the app stores them (productivity_percent, assignment_percent, interest_rate, ACC rate).
A12: Money | B12: NZD, excluding GST. Rates are per hour unless the column says otherwise.
A13: No names | B13: Staff are identified only by staff type and a row Ref. Assets and groups get a generic label.
A14: Headcount (Staff) / Count (Assets) | B14: How many identical copies of the row the generator creates. Use more rows for different rates within one staff type.
A15: Ref columns | B15: Short IDs (S01, A01, G01, C01) that link the sheets. Keep them unique.
A17: SHEETS
A18: Business | B18: Mode, year, materials markup, non-productive policy, owner labour treatment (open question Q-1), opening hours.
A19: Staff | B19: One row per staff type and rate band. Feeds qs_tools_labour_profiles_v1.
A20: Charge_Out | B20: Charge-out rate per staff type. Feeds qstools_rate_builder_labour_source_rates_v1 (rates live per staff type, not per person).
A21: Assets | B21: One row per asset (Count clones it). Feeds qs_tools_saved_assets.
A22: Groups | B22: Working groups. Feeds qs_tools_cost_allocation_v2_1 operational_groups.
A23: Labour_Assign | B23: Percent of each staff TYPE's whole pool assigned to a group (the app pools staff by type, register H1). Whole numbers; the app rounds to integers (H2).
A24: Asset_Assign | B24: Which assets sit in which group, and at what percent.
A25: Rate_Builder | B25: Calculator lines. A line linked to an asset makes a per-asset calculator (Path B).
A26: PnL | B26: Revenue, direct costs and overheads. Labour lines (wages, KiwiSaver, ACC) and asset interest are DERIVED by the generator from Staff and Assets, bottom-up (stress brief 3.1).
A27: Checks | B27: Totals and red flags. Every flag should read OK before the template is used.
A28: Lists | B28: Dropdown values. Do not edit.
A30: SCALING
A31: Scale ladder | B31: Keep this file as the base shape. The generator multiplies Headcount and Count by the ladder factor (10, 100, 1,000+ staff) without changing the shape (stress brief 3.3).
A33: SOURCE | B33: Field names and allowed values are taken from lib/storage/*.js and the :3004 localStorage dump of 2026-10-17. See STORAGE_KEY_REGISTER_S0_2026-10-17.txt.

Sheet Business
A1: Business settings
A2: Feeds qs_tools_business_setup_v1, qs_tools_revenue_cogs_state_v2, materials markup, non-productive policy, opening hours.
A4: Setting | B4: Value | C4: Stored as / notes
A5: Business label (generic) | B5: Stress Test Scenario A | C5: business_name. Generic label, no real name.
A6: Business type | B6: labour_based | C6: business_type. Hours mode for R2. Units mode is R4.
A7: Commercial driver mode | B7: hours_based | C7: commercial_driver_mode in Revenue/COGS.
A8: Financial year | B8: 2026 | C8: financial_year on the P&L (text).
A9: Materials markup (%) | C9: qstools_rate_builder_materials_markup_v1. Whole number, e.g. 20.
A10: Non-productive policy (mixed units) | B10: charge_to_self | C10: qstools_business_outcome_non_productive_policy_v1. Default charge_to_self.
A11: Owner labour treatment | C11: OPEN QUESTION Q-1. Wages in the P&L, or drawings (not in the P&L). Decides whether the owner row in Staff adds to the P&L labour lines.
A14: Opening hours (mirra_opening_hours_state_v4)
A15: Day | B15: Open (Y/N) | C15: Open time (hh:mm) | D15: Close time (hh:mm) | E15: Break (minutes) | F15: Open hours (check)
A16: Monday | B16: Y | C16: 08:00 | D16: 17:00 | E16: 0 | F16: =IF(AND(B16="Y",C16<>"",D16<>""),(TIMEVALUE(D16)-TIMEVALUE(C16))*24-E16/60,0) -> 9
A17: Tuesday | B17: Y | C17: 08:00 | D17: 17:00 | E17: 0 | F17: =IF(AND(B17="Y",C17<>"",D17<>""),(TIMEVALUE(D17)-TIMEVALUE(C17))*24-E17/60,0) -> 9
A18: Wednesday | B18: Y | C18: 08:00 | D18: 17:00 | E18: 0 | F18: =IF(AND(B18="Y",C18<>"",D18<>""),(TIMEVALUE(D18)-TIMEVALUE(C18))*24-E18/60,0) -> 9
A19: Thursday | B19: Y | C19: 08:00 | D19: 17:00 | E19: 0 | F19: =IF(AND(B19="Y",C19<>"",D19<>""),(TIMEVALUE(D19)-TIMEVALUE(C19))*24-E19/60,0) -> 9
A20: Friday | B20: Y | C20: 08:00 | D20: 17:00 | E20: 0 | F20: =IF(AND(B20="Y",C20<>"",D20<>""),(TIMEVALUE(D20)-TIMEVALUE(C20))*24-E20/60,0) -> 9
A21: Saturday | B21: N | E21: 0 | F21: =IF(AND(B21="Y",C21<>"",D21<>""),(TIMEVALUE(D21)-TIMEVALUE(C21))*24-E21/60,0) -> 0
A22: Sunday | B22: N | E22: 0 | F22: =IF(AND(B22="Y",C22<>"",D22<>""),(TIMEVALUE(D22)-TIMEVALUE(C22))*24-E22/60,0) -> 0
A23: Open hours per week | F23: =SUM(F16:F22) -> 45
A25: Seasonal shutdown (weeks) | B25: 4 | C25: seasonal_shutdown_weeks
A26: Public holiday days (closed) | B26: 0 | C26: public_holiday_days on the opening hours record (baseline 0; staff carry their own 12)

Sheet Staff
A1: Staff (one row per staff type and rate band)
A2: No names. Headcount = identical copies. Feeds qs_tools_labour_profiles_v1 (data block). Defaults are the app's DEFAULT_LABOUR_STATE.
A4: Ref | B4: staff_type_id | C4: Staff type (label) | D4: Headcount | E4: labour_class | F4: Contributes to recovery hours (Y/N) | G4: Hours per week | H4: Days per week | I4: Labour rate ($/hr) | J4: Productivity (%) | K4: Annual leave (weeks) | L4: Public holidays (days) | M4: Sick (days) | N4: Bereavement (days) | O4: Family violence (days) | P4: KiwiSaver employer (Y/N) | Q4: ACC enabled (Y/N) | R4: ACC rate (%) | S4: Base wages per person ($/yr, check) | T4: Base wages for row ($/yr, check) | U4: Notes
A5: EXAMPLE | B5: operator_delivery_staff | C5: Operator / Delivery Staff | D5: 4 | E5: productive | F5: Y | G5: 40 | H5: 5 | I5: 35 | J5: 85 | K5: 4 | L5: 12 | M5: 10 | N5: 1 | O5: 0 | P5: Y | Q5: Y | R5: 1.43 | S5: 72800 | T5: 291200 | U5: Example only - skipped by the generator
A6: S01 | B6: operator_delivery_staff | C6: =IFERROR(INDEX(Lists!$B$2:$B$11,MATCH(B6,Lists!$A$2:$A$11,0)),"") -> Operator / Delivery Staff | D6: 4 | E6: productive | F6: Y | G6: 40 | H6: 5 | J6: 85 | K6: 4 | L6: 12 | M6: 10 | N6: 1 | O6: 0 | P6: Y | Q6: Y | R6: 1.43 | S6: =IF(OR(G6="",I6=""),0,G6*52*I6) -> 0 | T6: =S6*D6 -> 0 | U6: Scenario A: 7 productive
A7: S02 | B7: senior_operator_staff | C7: =IFERROR(INDEX(Lists!$B$2:$B$11,MATCH(B7,Lists!$A$2:$A$11,0)),"") -> Senior Operator / Senior Staff | D7: 2 | E7: productive | F7: Y | G7: 40 | H7: 5 | J7: 85 | K7: 4 | L7: 12 | M7: 10 | N7: 1 | O7: 0 | P7: Y | Q7: Y | R7: 1.43 | S7: =IF(OR(G7="",I7=""),0,G7*52*I7) -> 0 | T7: =S7*D7 -> 0
A8: S03 | B8: supervisor_team_lead | C8: =IFERROR(INDEX(Lists!$B$2:$B$11,MATCH(B8,Lists!$A$2:$A$11,0)),"") -> Supervisor / Team Lead | D8: 1 | E8: productive | F8: Y | G8: 40 | H8: 5 | J8: 85 | K8: 4 | L8: 12 | M8: 10 | N8: 1 | O8: 0 | P8: Y | Q8: Y | R8: 1.43 | S8: =IF(OR(G8="",I8=""),0,G8*52*I8) -> 0 | T8: =S8*D8 -> 0
A9: S04 | B9: owner_director | C9: =IFERROR(INDEX(Lists!$B$2:$B$11,MATCH(B9,Lists!$A$2:$A$11,0)),"") -> Owner / Director | D9: 1 | E9: non_productive | F9: N | G9: 40 | H9: 5 | J9: 85 | K9: 4 | L9: 12 | M9: 10 | N9: 1 | O9: 0 | P9: Y | Q9: Y | R9: 1.43 | S9: =IF(OR(G9="",I9=""),0,G9*52*I9) -> 0 | T9: =S9*D9 -> 0 | U9: See Owner labour treatment on Business
A10: S05 | B10: admin_support | C10: =IFERROR(INDEX(Lists!$B$2:$B$11,MATCH(B10,Lists!$A$2:$A$11,0)),"") -> Administration / Support | D10: 1 | E10: non_productive | F10: N | G10: 40 | H10: 5 | J10: 85 | K10: 4 | L10: 12 | M10: 10 | N10: 1 | O10: 0 | P10: Y | Q10: Y | R10: 1.43 | S10: =IF(OR(G10="",I10=""),0,G10*52*I10) -> 0 | T10: =S10*D10 -> 0 | U10: Scenario A: 3 non-productive
A11: S06 | B11: finance_accounts | C11: =IFERROR(INDEX(Lists!$B$2:$B$11,MATCH(B11,Lists!$A$2:$A$11,0)),"") -> Finance / Accounts | D11: 1 | E11: non_productive | F11: N | G11: 40 | H11: 5 | J11: 85 | K11: 4 | L11: 12 | M11: 10 | N11: 1 | O11: 0 | P11: Y | Q11: Y | R11: 1.43 | S11: =IF(OR(G11="",I11=""),0,G11*52*I11) -> 0 | T11: =S11*D11 -> 0
A12: S07 | C12: =IFERROR(INDEX(Lists!$B$2:$B$11,MATCH(B12,Lists!$A$2:$A$11,0)),"") | S12: =IF(OR(G12="",I12=""),0,G12*52*I12) -> 0 | T12: =S12*D12 -> 0
A13: S08 | C13: =IFERROR(INDEX(Lists!$B$2:$B$11,MATCH(B13,Lists!$A$2:$A$11,0)),"") | S13: =IF(OR(G13="",I13=""),0,G13*52*I13) -> 0 | T13: =S13*D13 -> 0
A14: S09 | C14: =IFERROR(INDEX(Lists!$B$2:$B$11,MATCH(B14,Lists!$A$2:$A$11,0)),"") | S14: =IF(OR(G14="",I14=""),0,G14*52*I14) -> 0 | T14: =S14*D14 -> 0
A15: S10 | C15: =IFERROR(INDEX(Lists!$B$2:$B$11,MATCH(B15,Lists!$A$2:$A$11,0)),"") | S15: =IF(OR(G15="",I15=""),0,G15*52*I15) -> 0 | T15: =S15*D15 -> 0
A16: S11 | C16: =IFERROR(INDEX(Lists!$B$2:$B$11,MATCH(B16,Lists!$A$2:$A$11,0)),"") | S16: =IF(OR(G16="",I16=""),0,G16*52*I16) -> 0 | T16: =S16*D16 -> 0
A17: S12 | C17: =IFERROR(INDEX(Lists!$B$2:$B$11,MATCH(B17,Lists!$A$2:$A$11,0)),"") | S17: =IF(OR(G17="",I17=""),0,G17*52*I17) -> 0 | T17: =S17*D17 -> 0
A18: S13 | C18: =IFERROR(INDEX(Lists!$B$2:$B$11,MATCH(B18,Lists!$A$2:$A$11,0)),"") | S18: =IF(OR(G18="",I18=""),0,G18*52*I18) -> 0 | T18: =S18*D18 -> 0
A19: S14 | C19: =IFERROR(INDEX(Lists!$B$2:$B$11,MATCH(B19,Lists!$A$2:$A$11,0)),"") | S19: =IF(OR(G19="",I19=""),0,G19*52*I19) -> 0 | T19: =S19*D19 -> 0
A20: S15 | C20: =IFERROR(INDEX(Lists!$B$2:$B$11,MATCH(B20,Lists!$A$2:$A$11,0)),"") | S20: =IF(OR(G20="",I20=""),0,G20*52*I20) -> 0 | T20: =S20*D20 -> 0
A21: S16 | C21: =IFERROR(INDEX(Lists!$B$2:$B$11,MATCH(B21,Lists!$A$2:$A$11,0)),"") | S21: =IF(OR(G21="",I21=""),0,G21*52*I21) -> 0 | T21: =S21*D21 -> 0
A22: S17 | C22: =IFERROR(INDEX(Lists!$B$2:$B$11,MATCH(B22,Lists!$A$2:$A$11,0)),"") | S22: =IF(OR(G22="",I22=""),0,G22*52*I22) -> 0 | T22: =S22*D22 -> 0
A23: S18 | C23: =IFERROR(INDEX(Lists!$B$2:$B$11,MATCH(B23,Lists!$A$2:$A$11,0)),"") | S23: =IF(OR(G23="",I23=""),0,G23*52*I23) -> 0 | T23: =S23*D23 -> 0
... A30: S25 | C30: =IFERROR(INDEX(Lists!$B$2:$B$11,MATCH(B30,Lists!$A$2:$A$11,0)),"") | S30: =IF(OR(G30="",I30=""),0,G30*52*I30) -> 0 | T30: =S30*D30 -> 0
A32: Totals | D32: =SUM(D6:D30) -> 10 | T32: =SUM(T6:T30) -> 0
A33: The wage check is hours x 52 x rate only. Leave, KiwiSaver, ACC and productivity are applied by the app and by the expected-value script, not here.
A34: Custom staff types: add the id in column B (e.g. custom_crew_a). The generator also writes it to qs_tools_labour_staff_types_v1. Not used in Scenario A (strategy: few system types, percent splits).

Sheet Charge_Out
A1: Charge-out rate per staff type
A2: Rates live per staff type in qstools_rate_builder_labour_source_rates_v1. Only types used on Staff need a rate.
A4: staff_type_id | B4: Staff type | C4: Charge-out rate ($/hr) | D4: Productive headcount on Staff (check) | E4: Total headcount on Staff (check) | F4: Flag
A5: owner_director | B5: Owner / Director | D5: =SUMIFS(Staff!$D$6:$D$30,Staff!$B$6:$B$30,A5,Staff!$E$6:$E$30,"productive") -> 0 | E5: =SUMIFS(Staff!$D$6:$D$30,Staff!$B$6:$B$30,A5) -> 1 | F5: =IF(AND(D5>0,OR(C5="",C5=0)),"MISSING RATE - productive type with no charge-out","OK") -> OK
A6: manager | B6: Manager | D6: =SUMIFS(Staff!$D$6:$D$30,Staff!$B$6:$B$30,A6,Staff!$E$6:$E$30,"productive") -> 0 | E6: =SUMIFS(Staff!$D$6:$D$30,Staff!$B$6:$B$30,A6) -> 0 | F6: =IF(AND(D6>0,OR(C6="",C6=0)),"MISSING RATE - productive type with no charge-out","OK") -> OK
A7: supervisor_team_lead | B7: Supervisor / Team Lead | D7: =SUMIFS(Staff!$D$6:$D$30,Staff!$B$6:$B$30,A7,Staff!$E$6:$E$30,"productive") -> 1 | E7: =SUMIFS(Staff!$D$6:$D$30,Staff!$B$6:$B$30,A7) -> 1 | F7: =IF(AND(D7>0,OR(C7="",C7=0)),"MISSING RATE - productive type with no charge-out","OK") -> MISSING RATE - productive type with no charge-out
A8: senior_operator_staff | B8: Senior Operator / Senior Staff | D8: =SUMIFS(Staff!$D$6:$D$30,Staff!$B$6:$B$30,A8,Staff!$E$6:$E$30,"productive") -> 2 | E8: =SUMIFS(Staff!$D$6:$D$30,Staff!$B$6:$B$30,A8) -> 2 | F8: =IF(AND(D8>0,OR(C8="",C8=0)),"MISSING RATE - productive type with no charge-out","OK") -> MISSING RATE - productive type with no charge-out
A9: operator_delivery_staff | B9: Operator / Delivery Staff | D9: =SUMIFS(Staff!$D$6:$D$30,Staff!$B$6:$B$30,A9,Staff!$E$6:$E$30,"productive") -> 4 | E9: =SUMIFS(Staff!$D$6:$D$30,Staff!$B$6:$B$30,A9) -> 4 | F9: =IF(AND(D9>0,OR(C9="",C9=0)),"MISSING RATE - productive type with no charge-out","OK") -> MISSING RATE - productive type with no charge-out
A10: junior_trainee | B10: Junior / Trainee | D10: =SUMIFS(Staff!$D$6:$D$30,Staff!$B$6:$B$30,A10,Staff!$E$6:$E$30,"productive") -> 0 | E10: =SUMIFS(Staff!$D$6:$D$30,Staff!$B$6:$B$30,A10) -> 0 | F10: =IF(AND(D10>0,OR(C10="",C10=0)),"MISSING RATE - productive type with no charge-out","OK") -> OK
A11: admin_support | B11: Administration / Support | D11: =SUMIFS(Staff!$D$6:$D$30,Staff!$B$6:$B$30,A11,Staff!$E$6:$E$30,"productive") -> 0 | E11: =SUMIFS(Staff!$D$6:$D$30,Staff!$B$6:$B$30,A11) -> 1 | F11: =IF(AND(D11>0,OR(C11="",C11=0)),"MISSING RATE - productive type with no charge-out","OK") -> OK
A12: sales_customer_support | B12: Sales / Customer Support | D12: =SUMIFS(Staff!$D$6:$D$30,Staff!$B$6:$B$30,A12,Staff!$E$6:$E$30,"productive") -> 0 | E12: =SUMIFS(Staff!$D$6:$D$30,Staff!$B$6:$B$30,A12) -> 0 | F12: =IF(AND(D12>0,OR(C12="",C12=0)),"MISSING RATE - productive type with no charge-out","OK") -> OK
A13: finance_accounts | B13: Finance / Accounts | D13: =SUMIFS(Staff!$D$6:$D$30,Staff!$B$6:$B$30,A13,Staff!$E$6:$E$30,"productive") -> 0 | E13: =SUMIFS(Staff!$D$6:$D$30,Staff!$B$6:$B$30,A13) -> 1 | F13: =IF(AND(D13>0,OR(C13="",C13=0)),"MISSING RATE - productive type with no charge-out","OK") -> OK
A14: other_review_required | B14: Other / Review required | D14: =SUMIFS(Staff!$D$6:$D$30,Staff!$B$6:$B$30,A14,Staff!$E$6:$E$30,"productive") -> 0 | E14: =SUMIFS(Staff!$D$6:$D$30,Staff!$B$6:$B$30,A14) -> 0 | F14: =IF(AND(D14>0,OR(C14="",C14=0)),"MISSING RATE - productive type with no charge-out","OK") -> OK

Sheet Assets
A1: Assets (one row per asset; Count clones it)
A2: Feeds qs_tools_saved_assets. Only inputs here - the app recomputes finance and cost fields on read. Generic labels only.
A4: Ref | B4: Label (generic) | C4: Count | D4: asset_type | E4: Utilisation hours per week | F4: Downtime hours per week | G4: Annual weeks | H4: Purchase price ($) | I4: Interest rate (%) | J4: Finance start date (yyyy-mm-dd) | K4: Finance term (years) | L4: Finance paid off (Y/N) | M4: Maintenance ($/month) | N4: Fuel ($/month) | O4: Registration ($/month) | P4: Other running ($/month) | Q4: Include depreciation in cost (Y/N) | R4: Estimated annual depreciation ($) | S4: Annual hours (check) | T4: Running cost $/yr (check) | U4: Notes
A5: EXAMPLE | B5: Productive asset (example) | C5: 1 | D5: productive | E5: 30 | F5: 0 | G5: 48 | H5: 200000 | I5: 10 | J5: 2026-10-02 | K5: 5 | L5: N | M5: 500 | N5: 800 | O5: 100 | P5: 0 | Q5: N | S5: 1440 | T5: 16800 | U5: Example only - skipped
A6: A01 | B6: Productive asset 1 | C6: 1 | D6: productive | E6: 40 | F6: 0 | G6: 48 | K6: 0 | L6: N | M6: 0 | N6: 0 | O6: 0 | P6: 0 | Q6: N | S6: =MAX(0,E6-F6)*G6 -> 1920 | T6: =(M6+N6+O6+P6)*12 -> 0 | U6: Scenario A: 4 productive
A7: A02 | B7: Productive asset 2 | C7: 1 | D7: productive | E7: 40 | F7: 0 | G7: 48 | K7: 0 | L7: N | M7: 0 | N7: 0 | O7: 0 | P7: 0 | Q7: N | S7: =MAX(0,E7-F7)*G7 -> 1920 | T7: =(M7+N7+O7+P7)*12 -> 0
A8: A03 | B8: Productive asset 3 | C8: 1 | D8: productive | E8: 40 | F8: 0 | G8: 48 | K8: 0 | L8: N | M8: 0 | N8: 0 | O8: 0 | P8: 0 | Q8: N | S8: =MAX(0,E8-F8)*G8 -> 1920 | T8: =(M8+N8+O8+P8)*12 -> 0
A9: A04 | B9: Productive asset 4 | C9: 1 | D9: productive | E9: 40 | F9: 0 | G9: 48 | K9: 0 | L9: N | M9: 0 | N9: 0 | O9: 0 | P9: 0 | Q9: N | S9: =MAX(0,E9-F9)*G9 -> 1920 | T9: =(M9+N9+O9+P9)*12 -> 0
A10: A05 | B10: Support asset 1 | C10: 1 | D10: support | E10: 0 | F10: 0 | G10: 48 | K10: 0 | L10: N | M10: 0 | N10: 0 | O10: 0 | P10: 0 | Q10: N | S10: =MAX(0,E10-F10)*G10 -> 0 | T10: =(M10+N10+O10+P10)*12 -> 0 | U10: Scenario A: 3 support (non-productive)
A11: A06 | B11: Support asset 2 | C11: 1 | D11: support | E11: 0 | F11: 0 | G11: 48 | K11: 0 | L11: N | M11: 0 | N11: 0 | O11: 0 | P11: 0 | Q11: N | S11: =MAX(0,E11-F11)*G11 -> 0 | T11: =(M11+N11+O11+P11)*12 -> 0
A12: A07 | B12: Support asset 3 | C12: 1 | D12: support | E12: 0 | F12: 0 | G12: 48 | K12: 0 | L12: N | M12: 0 | N12: 0 | O12: 0 | P12: 0 | Q12: N | S12: =MAX(0,E12-F12)*G12 -> 0 | T12: =(M12+N12+O12+P12)*12 -> 0
A13: A08 | S13: =MAX(0,E13-F13)*G13 -> 0 | T13: =(M13+N13+O13+P13)*12 -> 0
A14: A09 | S14: =MAX(0,E14-F14)*G14 -> 0 | T14: =(M14+N14+O14+P14)*12 -> 0
A15: A10 | S15: =MAX(0,E15-F15)*G15 -> 0 | T15: =(M15+N15+O15+P15)*12 -> 0
A16: A11 | S16: =MAX(0,E16-F16)*G16 -> 0 | T16: =(M16+N16+O16+P16)*12 -> 0
A17: A12 | S17: =MAX(0,E17-F17)*G17 -> 0 | T17: =(M17+N17+O17+P17)*12 -> 0
A18: A13 | S18: =MAX(0,E18-F18)*G18 -> 0 | T18: =(M18+N18+O18+P18)*12 -> 0
A19: A14 | S19: =MAX(0,E19-F19)*G19 -> 0 | T19: =(M19+N19+O19+P19)*12 -> 0
A20: A15 | S20: =MAX(0,E20-F20)*G20 -> 0 | T20: =(M20+N20+O20+P20)*12 -> 0
A21: A16 | S21: =MAX(0,E21-F21)*G21 -> 0 | T21: =(M21+N21+O21+P21)*12 -> 0
A22: A17 | S22: =MAX(0,E22-F22)*G22 -> 0 | T22: =(M22+N22+O22+P22)*12 -> 0
A23: A18 | S23: =MAX(0,E23-F23)*G23 -> 0 | T23: =(M23+N23+O23+P23)*12 -> 0
A24: A19 | S24: =MAX(0,E24-F24)*G24 -> 0 | T24: =(M24+N24+O24+P24)*12 -> 0
A25: A20 | S25: =MAX(0,E25-F25)*G25 -> 0 | T25: =(M25+N25+O25+P25)*12 -> 0
A27: Annual weeks 48 is the app default (ASSET_UTILISATION_WEEKS_PER_YEAR). Running cost check is the monthly costs x 12. Asset overhead pool assignments default to 0 (not in this template).

Sheet Groups
A1: Working groups
A2: Feeds operational_groups in qs_tools_cost_allocation_v2_1. Division is Main Operations for every group unless you add more.
A4: Ref | B4: Group label (generic) | C4: Recovery hour source | D4: Asset run pattern | E4: Labour tied to asset (Y/N) | F4: Labour rows assigned (check) | G4: Assets assigned (check) | H4: Flag | I4: Notes
A5: EXAMPLE | B5: Excavator unit | C5: asset_hours | D5: together | E5: N | I5: Example only - skipped
A6: G01 | B6: Asset unit 1 | C6: asset_hours | D6: together | E6: N | F6: =COUNTIFS(Labour_Assign!$A$6:$A$60,A6,Labour_Assign!$C$6:$C$60,">0") -> 0 | G6: =COUNTIFS(Asset_Assign!$A$6:$A$60,A6) -> 2 | H6: =IF(B6="","",IF(AND(C6="asset_hours",G6=0),"asset_hours group with no assets",IF(F6=0,"no labour assigned",IF(AND(E6="Y",C6<>"asset_hours"),"tie box only applies to asset_hours groups","OK")))) -> no labour assigned | I6: Assets A01-A02 with operators
A7: G02 | B7: Asset unit 2 | C7: asset_hours | D7: together | E7: N | F7: =COUNTIFS(Labour_Assign!$A$6:$A$60,A7,Labour_Assign!$C$6:$C$60,">0") -> 0 | G7: =COUNTIFS(Asset_Assign!$A$6:$A$60,A7) -> 2 | H7: =IF(B7="","",IF(AND(C7="asset_hours",G7=0),"asset_hours group with no assets",IF(F7=0,"no labour assigned",IF(AND(E7="Y",C7<>"asset_hours"),"tie box only applies to asset_hours groups","OK")))) -> no labour assigned | I7: Assets A03-A04
A8: G03 | B8: Labour crew | C8: labour_hours | D8: together | E8: N | F8: =COUNTIFS(Labour_Assign!$A$6:$A$60,A8,Labour_Assign!$C$6:$C$60,">0") -> 0 | G8: =COUNTIFS(Asset_Assign!$A$6:$A$60,A8) -> 0 | H8: =IF(B8="","",IF(AND(C8="asset_hours",G8=0),"asset_hours group with no assets",IF(F8=0,"no labour assigned",IF(AND(E8="Y",C8<>"asset_hours"),"tie box only applies to asset_hours groups","OK")))) -> no labour assigned | I8: Labour-only work
A9: G04 | B9: Office and support | C9: labour_hours | D9: together | E9: N | F9: =COUNTIFS(Labour_Assign!$A$6:$A$60,A9,Labour_Assign!$C$6:$C$60,">0") -> 0 | G9: =COUNTIFS(Asset_Assign!$A$6:$A$60,A9) -> 0 | H9: =IF(B9="","",IF(AND(C9="asset_hours",G9=0),"asset_hours group with no assets",IF(F9=0,"no labour assigned",IF(AND(E9="Y",C9<>"asset_hours"),"tie box only applies to asset_hours groups","OK")))) -> no labour assigned | I9: Non-productive staff
A10: G05 | F10: =COUNTIFS(Labour_Assign!$A$6:$A$60,A10,Labour_Assign!$C$6:$C$60,">0") -> 0 | G10: =COUNTIFS(Asset_Assign!$A$6:$A$60,A10) -> 0 | H10: =IF(B10="","",IF(AND(C10="asset_hours",G10=0),"asset_hours group with no assets",IF(F10=0,"no labour assigned",IF(AND(E10="Y",C10<>"asset_hours"),"tie box only applies to asset_hours groups","OK"))))
A11: G06 | F11: =COUNTIFS(Labour_Assign!$A$6:$A$60,A11,Labour_Assign!$C$6:$C$60,">0") -> 0 | G11: =COUNTIFS(Asset_Assign!$A$6:$A$60,A11) -> 0 | H11: =IF(B11="","",IF(AND(C11="asset_hours",G11=0),"asset_hours group with no assets",IF(F11=0,"no labour assigned",IF(AND(E11="Y",C11<>"asset_hours"),"tie box only applies to asset_hours groups","OK"))))
A12: G07 | F12: =COUNTIFS(Labour_Assign!$A$6:$A$60,A12,Labour_Assign!$C$6:$C$60,">0") -> 0 | G12: =COUNTIFS(Asset_Assign!$A$6:$A$60,A12) -> 0 | H12: =IF(B12="","",IF(AND(C12="asset_hours",G12=0),"asset_hours group with no assets",IF(F12=0,"no labour assigned",IF(AND(E12="Y",C12<>"asset_hours"),"tie box only applies to asset_hours groups","OK"))))
A13: G08 | F13: =COUNTIFS(Labour_Assign!$A$6:$A$60,A13,Labour_Assign!$C$6:$C$60,">0") -> 0 | G13: =COUNTIFS(Asset_Assign!$A$6:$A$60,A13) -> 0 | H13: =IF(B13="","",IF(AND(C13="asset_hours",G13=0),"asset_hours group with no assets",IF(F13=0,"no labour assigned",IF(AND(E13="Y",C13<>"asset_hours"),"tie box only applies to asset_hours groups","OK"))))
A14: G09 | F14: =COUNTIFS(Labour_Assign!$A$6:$A$60,A14,Labour_Assign!$C$6:$C$60,">0") -> 0 | G14: =COUNTIFS(Asset_Assign!$A$6:$A$60,A14) -> 0 | H14: =IF(B14="","",IF(AND(C14="asset_hours",G14=0),"asset_hours group with no assets",IF(F14=0,"no labour assigned",IF(AND(E14="Y",C14<>"asset_hours"),"tie box only applies to asset_hours groups","OK"))))
A15: G10 | F15: =COUNTIFS(Labour_Assign!$A$6:$A$60,A15,Labour_Assign!$C$6:$C$60,">0") -> 0 | G15: =COUNTIFS(Asset_Assign!$A$6:$A$60,A15) -> 0 | H15: =IF(B15="","",IF(AND(C15="asset_hours",G15=0),"asset_hours group with no assets",IF(F15=0,"no labour assigned",IF(AND(E15="Y",C15<>"asset_hours"),"tie box only applies to asset_hours groups","OK"))))
A17: Asset run pattern: together = assets run at the same time (required hours = MAX); sequential = one after another (SUM). Stored as "" or "sequential".

Sheet Labour_Assign
A1: Labour assignment - percent of each staff TYPE's pool per group
A2: The app pools every person of a type, then assigns a percent of that pool (register H1). Whole numbers only (H2).
A4: Group Ref | B4: staff_type_id | C4: Assignment (%) | D4: Group label (check) | E4: Type total % across groups (check) | F4: Flag
A5: EXAMPLE | B5: operator_delivery_staff | C5: 50 | D5: Asset unit 1 | E5: 100 | F5: Example only - skipped
A6: G01 | B6: operator_delivery_staff | D6: =IF(A6="","",IFERROR(INDEX(Groups!$B$6:$B$15,MATCH(A6,Groups!$A$6:$A$15,0)),"UNKNOWN GROUP")) -> Asset unit 1 | E6: =IF(B6="","",SUMIFS($C$6:$C$60,$B$6:$B$60,B6)) -> 0 | F6: =IF(B6="","",IF(COUNTIFS(Staff!$B$6:$B$30,B6)=0,"type not on Staff",IF(C6<>INT(C6),"not a whole number - app rounds it",IF(E6>100,"type over 100% across groups",IF(E6<100,"type under 100% - unassigned cost","OK"))))) -> type under 100% - unassigned cost
A7: G02 | B7: operator_delivery_staff | D7: =IF(A7="","",IFERROR(INDEX(Groups!$B$6:$B$15,MATCH(A7,Groups!$A$6:$A$15,0)),"UNKNOWN GROUP")) -> Asset unit 2 | E7: =IF(B7="","",SUMIFS($C$6:$C$60,$B$6:$B$60,B7)) -> 0 | F7: =IF(B7="","",IF(COUNTIFS(Staff!$B$6:$B$30,B7)=0,"type not on Staff",IF(C7<>INT(C7),"not a whole number - app rounds it",IF(E7>100,"type over 100% across groups",IF(E7<100,"type under 100% - unassigned cost","OK"))))) -> type under 100% - unassigned cost
A8: G03 | B8: operator_delivery_staff | D8: =IF(A8="","",IFERROR(INDEX(Groups!$B$6:$B$15,MATCH(A8,Groups!$A$6:$A$15,0)),"UNKNOWN GROUP")) -> Labour crew | E8: =IF(B8="","",SUMIFS($C$6:$C$60,$B$6:$B$60,B8)) -> 0 | F8: =IF(B8="","",IF(COUNTIFS(Staff!$B$6:$B$30,B8)=0,"type not on Staff",IF(C8<>INT(C8),"not a whole number - app rounds it",IF(E8>100,"type over 100% across groups",IF(E8<100,"type under 100% - unassigned cost","OK"))))) -> type under 100% - unassigned cost
A9: G01 | B9: senior_operator_staff | D9: =IF(A9="","",IFERROR(INDEX(Groups!$B$6:$B$15,MATCH(A9,Groups!$A$6:$A$15,0)),"UNKNOWN GROUP")) -> Asset unit 1 | E9: =IF(B9="","",SUMIFS($C$6:$C$60,$B$6:$B$60,B9)) -> 0 | F9: =IF(B9="","",IF(COUNTIFS(Staff!$B$6:$B$30,B9)=0,"type not on Staff",IF(C9<>INT(C9),"not a whole number - app rounds it",IF(E9>100,"type over 100% across groups",IF(E9<100,"type under 100% - unassigned cost","OK"))))) -> type under 100% - unassigned cost
A10: G02 | B10: senior_operator_staff | D10: =IF(A10="","",IFERROR(INDEX(Groups!$B$6:$B$15,MATCH(A10,Groups!$A$6:$A$15,0)),"UNKNOWN GROUP")) -> Asset unit 2 | E10: =IF(B10="","",SUMIFS($C$6:$C$60,$B$6:$B$60,B10)) -> 0 | F10: =IF(B10="","",IF(COUNTIFS(Staff!$B$6:$B$30,B10)=0,"type not on Staff",IF(C10<>INT(C10),"not a whole number - app rounds it",IF(E10>100,"type over 100% across groups",IF(E10<100,"type under 100% - unassigned cost","OK"))))) -> type under 100% - unassigned cost
A11: G03 | B11: supervisor_team_lead | D11: =IF(A11="","",IFERROR(INDEX(Groups!$B$6:$B$15,MATCH(A11,Groups!$A$6:$A$15,0)),"UNKNOWN GROUP")) -> Labour crew | E11: =IF(B11="","",SUMIFS($C$6:$C$60,$B$6:$B$60,B11)) -> 0 | F11: =IF(B11="","",IF(COUNTIFS(Staff!$B$6:$B$30,B11)=0,"type not on Staff",IF(C11<>INT(C11),"not a whole number - app rounds it",IF(E11>100,"type over 100% across groups",IF(E11<100,"type under 100% - unassigned cost","OK"))))) -> type under 100% - unassigned cost
A12: G04 | B12: owner_director | D12: =IF(A12="","",IFERROR(INDEX(Groups!$B$6:$B$15,MATCH(A12,Groups!$A$6:$A$15,0)),"UNKNOWN GROUP")) -> Office and support | E12: =IF(B12="","",SUMIFS($C$6:$C$60,$B$6:$B$60,B12)) -> 0 | F12: =IF(B12="","",IF(COUNTIFS(Staff!$B$6:$B$30,B12)=0,"type not on Staff",IF(C12<>INT(C12),"not a whole number - app rounds it",IF(E12>100,"type over 100% across groups",IF(E12<100,"type under 100% - unassigned cost","OK"))))) -> type under 100% - unassigned cost
A13: G04 | B13: admin_support | D13: =IF(A13="","",IFERROR(INDEX(Groups!$B$6:$B$15,MATCH(A13,Groups!$A$6:$A$15,0)),"UNKNOWN GROUP")) -> Office and support | E13: =IF(B13="","",SUMIFS($C$6:$C$60,$B$6:$B$60,B13)) -> 0 | F13: =IF(B13="","",IF(COUNTIFS(Staff!$B$6:$B$30,B13)=0,"type not on Staff",IF(C13<>INT(C13),"not a whole number - app rounds it",IF(E13>100,"type over 100% across groups",IF(E13<100,"type under 100% - unassigned cost","OK"))))) -> type under 100% - unassigned cost
A14: G04 | B14: finance_accounts | D14: =IF(A14="","",IFERROR(INDEX(Groups!$B$6:$B$15,MATCH(A14,Groups!$A$6:$A$15,0)),"UNKNOWN GROUP")) -> Office and support | E14: =IF(B14="","",SUMIFS($C$6:$C$60,$B$6:$B$60,B14)) -> 0 | F14: =IF(B14="","",IF(COUNTIFS(Staff!$B$6:$B$30,B14)=0,"type not on Staff",IF(C14<>INT(C14),"not a whole number - app rounds it",IF(E14>100,"type over 100% across groups",IF(E14<100,"type under 100% - unassigned cost","OK"))))) -> type under 100% - unassigned cost
D15: =IF(A15="","",IFERROR(INDEX(Groups!$B$6:$B$15,MATCH(A15,Groups!$A$6:$A$15,0)),"UNKNOWN GROUP")) | E15: =IF(B15="","",SUMIFS($C$6:$C$60,$B$6:$B$60,B15)) | F15: =IF(B15="","",IF(COUNTIFS(Staff!$B$6:$B$30,B15)=0,"type not on Staff",IF(C15<>INT(C15),"not a whole number - app rounds it",IF(E15>100,"type over 100% across groups",IF(E15<100,"type under 100% - unassigned cost","OK")))))
D16: =IF(A16="","",IFERROR(INDEX(Groups!$B$6:$B$15,MATCH(A16,Groups!$A$6:$A$15,0)),"UNKNOWN GROUP")) | E16: =IF(B16="","",SUMIFS($C$6:$C$60,$B$6:$B$60,B16)) | F16: =IF(B16="","",IF(COUNTIFS(Staff!$B$6:$B$30,B16)=0,"type not on Staff",IF(C16<>INT(C16),"not a whole number - app rounds it",IF(E16>100,"type over 100% across groups",IF(E16<100,"type under 100% - unassigned cost","OK")))))
D17: =IF(A17="","",IFERROR(INDEX(Groups!$B$6:$B$15,MATCH(A17,Groups!$A$6:$A$15,0)),"UNKNOWN GROUP")) | E17: =IF(B17="","",SUMIFS($C$6:$C$60,$B$6:$B$60,B17)) | F17: =IF(B17="","",IF(COUNTIFS(Staff!$B$6:$B$30,B17)=0,"type not on Staff",IF(C17<>INT(C17),"not a whole number - app rounds it",IF(E17>100,"type over 100% across groups",IF(E17<100,"type under 100% - unassigned cost","OK")))))
D18: =IF(A18="","",IFERROR(INDEX(Groups!$B$6:$B$15,MATCH(A18,Groups!$A$6:$A$15,0)),"UNKNOWN GROUP")) | E18: =IF(B18="","",SUMIFS($C$6:$C$60,$B$6:$B$60,B18)) | F18: =IF(B18="","",IF(COUNTIFS(Staff!$B$6:$B$30,B18)=0,"type not on Staff",IF(C18<>INT(C18),"not a whole number - app rounds it",IF(E18>100,"type over 100% across groups",IF(E18<100,"type under 100% - unassigned cost","OK")))))
D19: =IF(A19="","",IFERROR(INDEX(Groups!$B$6:$B$15,MATCH(A19,Groups!$A$6:$A$15,0)),"UNKNOWN GROUP")) | E19: =IF(B19="","",SUMIFS($C$6:$C$60,$B$6:$B$60,B19)) | F19: =IF(B19="","",IF(COUNTIFS(Staff!$B$6:$B$30,B19)=0,"type not on Staff",IF(C19<>INT(C19),"not a whole number - app rounds it",IF(E19>100,"type over 100% across groups",IF(E19<100,"type under 100% - unassigned cost","OK")))))
D20: =IF(A20="","",IFERROR(INDEX(Groups!$B$6:$B$15,MATCH(A20,Groups!$A$6:$A$15,0)),"UNKNOWN GROUP")) | E20: =IF(B20="","",SUMIFS($C$6:$C$60,$B$6:$B$60,B20)) | F20: =IF(B20="","",IF(COUNTIFS(Staff!$B$6:$B$30,B20)=0,"type not on Staff",IF(C20<>INT(C20),"not a whole number - app rounds it",IF(E20>100,"type over 100% across groups",IF(E20<100,"type under 100% - unassigned cost","OK")))))
D21: =IF(A21="","",IFERROR(INDEX(Groups!$B$6:$B$15,MATCH(A21,Groups!$A$6:$A$15,0)),"UNKNOWN GROUP")) | E21: =IF(B21="","",SUMIFS($C$6:$C$60,$B$6:$B$60,B21)) | F21: =IF(B21="","",IF(COUNTIFS(Staff!$B$6:$B$30,B21)=0,"type not on Staff",IF(C21<>INT(C21),"not a whole number - app rounds it",IF(E21>100,"type over 100% across groups",IF(E21<100,"type under 100% - unassigned cost","OK")))))
D22: =IF(A22="","",IFERROR(INDEX(Groups!$B$6:$B$15,MATCH(A22,Groups!$A$6:$A$15,0)),"UNKNOWN GROUP")) | E22: =IF(B22="","",SUMIFS($C$6:$C$60,$B$6:$B$60,B22)) | F22: =IF(B22="","",IF(COUNTIFS(Staff!$B$6:$B$30,B22)=0,"type not on Staff",IF(C22<>INT(C22),"not a whole number - app rounds it",IF(E22>100,"type over 100% across groups",IF(E22<100,"type under 100% - unassigned cost","OK")))))
D23: =IF(A23="","",IFERROR(INDEX(Groups!$B$6:$B$15,MATCH(A23,Groups!$A$6:$A$15,0)),"UNKNOWN GROUP")) | E23: =IF(B23="","",SUMIFS($C$6:$C$60,$B$6:$B$60,B23)) | F23: =IF(B23="","",IF(COUNTIFS(Staff!$B$6:$B$30,B23)=0,"type not on Staff",IF(C23<>INT(C23),"not a whole number - app rounds it",IF(E23>100,"type over 100% across groups",IF(E23<100,"type under 100% - unassigned cost","OK")))))
D24: =IF(A24="","",IFERROR(INDEX(Groups!$B$6:$B$15,MATCH(A24,Groups!$A$6:$A$15,0)),"UNKNOWN GROUP")) | E24: =IF(B24="","",SUMIFS($C$6:$C$60,$B$6:$B$60,B24)) | F24: =IF(B24="","",IF(COUNTIFS(Staff!$B$6:$B$30,B24)=0,"type not on Staff",IF(C24<>INT(C24),"not a whole number - app rounds it",IF(E24>100,"type over 100% across groups",IF(E24<100,"type under 100% - unassigned cost","OK")))))
D25: =IF(A25="","",IFERROR(INDEX(Groups!$B$6:$B$15,MATCH(A25,Groups!$A$6:$A$15,0)),"UNKNOWN GROUP")) | E25: =IF(B25="","",SUMIFS($C$6:$C$60,$B$6:$B$60,B25)) | F25: =IF(B25="","",IF(COUNTIFS(Staff!$B$6:$B$30,B25)=0,"type not on Staff",IF(C25<>INT(C25),"not a whole number - app rounds it",IF(E25>100,"type over 100% across groups",IF(E25<100,"type under 100% - unassigned cost","OK")))))
D26: =IF(A26="","",IFERROR(INDEX(Groups!$B$6:$B$15,MATCH(A26,Groups!$A$6:$A$15,0)),"UNKNOWN GROUP")) | E26: =IF(B26="","",SUMIFS($C$6:$C$60,$B$6:$B$60,B26)) | F26: =IF(B26="","",IF(COUNTIFS(Staff!$B$6:$B$30,B26)=0,"type not on Staff",IF(C26<>INT(C26),"not a whole number - app rounds it",IF(E26>100,"type over 100% across groups",IF(E26<100,"type under 100% - unassigned cost","OK")))))
... D60: =IF(A60="","",IFERROR(INDEX(Groups!$B$6:$B$15,MATCH(A60,Groups!$A$6:$A$15,0)),"UNKNOWN GROUP")) | E60: =IF(B60="","",SUMIFS($C$6:$C$60,$B$6:$B$60,B60)) | F60: =IF(B60="","",IF(COUNTIFS(Staff!$B$6:$B$30,B60)=0,"type not on Staff",IF(C60<>INT(C60),"not a whole number - app rounds it",IF(E60>100,"type over 100% across groups",IF(E60<100,"type under 100% - unassigned cost","OK")))))

Sheet Asset_Assign
A1: Asset assignment
A2: asset_group_assignments. One row per asset (or per clone set, matched on Ref) per group.
A4: Group Ref | B4: Asset Ref | C4: Assignment (%) | D4: Group label (check) | E4: Asset total % across groups (check) | F4: Flag
A5: EXAMPLE | B5: A01 | C5: 100 | D5: Asset unit 1 | E5: 100 | F5: Example only - skipped
A6: G01 | B6: A01 | C6: 100 | D6: =IF(A6="","",IFERROR(INDEX(Groups!$B$6:$B$15,MATCH(A6,Groups!$A$6:$A$15,0)),"UNKNOWN GROUP")) -> Asset unit 1 | E6: =IF(B6="","",SUMIFS($C$6:$C$60,$B$6:$B$60,B6)) -> 100 | F6: =IF(B6="","",IF(COUNTIFS(Assets!$A$6:$A$25,B6)=0,"asset not on Assets",IF(E6>100,"asset over 100% across groups (register H7)","OK"))) -> OK
A7: G01 | B7: A02 | C7: 100 | D7: =IF(A7="","",IFERROR(INDEX(Groups!$B$6:$B$15,MATCH(A7,Groups!$A$6:$A$15,0)),"UNKNOWN GROUP")) -> Asset unit 1 | E7: =IF(B7="","",SUMIFS($C$6:$C$60,$B$6:$B$60,B7)) -> 100 | F7: =IF(B7="","",IF(COUNTIFS(Assets!$A$6:$A$25,B7)=0,"asset not on Assets",IF(E7>100,"asset over 100% across groups (register H7)","OK"))) -> OK
A8: G02 | B8: A03 | C8: 100 | D8: =IF(A8="","",IFERROR(INDEX(Groups!$B$6:$B$15,MATCH(A8,Groups!$A$6:$A$15,0)),"UNKNOWN GROUP")) -> Asset unit 2 | E8: =IF(B8="","",SUMIFS($C$6:$C$60,$B$6:$B$60,B8)) -> 100 | F8: =IF(B8="","",IF(COUNTIFS(Assets!$A$6:$A$25,B8)=0,"asset not on Assets",IF(E8>100,"asset over 100% across groups (register H7)","OK"))) -> OK
A9: G02 | B9: A04 | C9: 100 | D9: =IF(A9="","",IFERROR(INDEX(Groups!$B$6:$B$15,MATCH(A9,Groups!$A$6:$A$15,0)),"UNKNOWN GROUP")) -> Asset unit 2 | E9: =IF(B9="","",SUMIFS($C$6:$C$60,$B$6:$B$60,B9)) -> 100 | F9: =IF(B9="","",IF(COUNTIFS(Assets!$A$6:$A$25,B9)=0,"asset not on Assets",IF(E9>100,"asset over 100% across groups (register H7)","OK"))) -> OK
D10: =IF(A10="","",IFERROR(INDEX(Groups!$B$6:$B$15,MATCH(A10,Groups!$A$6:$A$15,0)),"UNKNOWN GROUP")) | E10: =IF(B10="","",SUMIFS($C$6:$C$60,$B$6:$B$60,B10)) | F10: =IF(B10="","",IF(COUNTIFS(Assets!$A$6:$A$25,B10)=0,"asset not on Assets",IF(E10>100,"asset over 100% across groups (register H7)","OK")))
D11: =IF(A11="","",IFERROR(INDEX(Groups!$B$6:$B$15,MATCH(A11,Groups!$A$6:$A$15,0)),"UNKNOWN GROUP")) | E11: =IF(B11="","",SUMIFS($C$6:$C$60,$B$6:$B$60,B11)) | F11: =IF(B11="","",IF(COUNTIFS(Assets!$A$6:$A$25,B11)=0,"asset not on Assets",IF(E11>100,"asset over 100% across groups (register H7)","OK")))
D12: =IF(A12="","",IFERROR(INDEX(Groups!$B$6:$B$15,MATCH(A12,Groups!$A$6:$A$15,0)),"UNKNOWN GROUP")) | E12: =IF(B12="","",SUMIFS($C$6:$C$60,$B$6:$B$60,B12)) | F12: =IF(B12="","",IF(COUNTIFS(Assets!$A$6:$A$25,B12)=0,"asset not on Assets",IF(E12>100,"asset over 100% across groups (register H7)","OK")))
D13: =IF(A13="","",IFERROR(INDEX(Groups!$B$6:$B$15,MATCH(A13,Groups!$A$6:$A$15,0)),"UNKNOWN GROUP")) | E13: =IF(B13="","",SUMIFS($C$6:$C$60,$B$6:$B$60,B13)) | F13: =IF(B13="","",IF(COUNTIFS(Assets!$A$6:$A$25,B13)=0,"asset not on Assets",IF(E13>100,"asset over 100% across groups (register H7)","OK")))
D14: =IF(A14="","",IFERROR(INDEX(Groups!$B$6:$B$15,MATCH(A14,Groups!$A$6:$A$15,0)),"UNKNOWN GROUP")) | E14: =IF(B14="","",SUMIFS($C$6:$C$60,$B$6:$B$60,B14)) | F14: =IF(B14="","",IF(COUNTIFS(Assets!$A$6:$A$25,B14)=0,"asset not on Assets",IF(E14>100,"asset over 100% across groups (register H7)","OK")))
D15: =IF(A15="","",IFERROR(INDEX(Groups!$B$6:$B$15,MATCH(A15,Groups!$A$6:$A$15,0)),"UNKNOWN GROUP")) | E15: =IF(B15="","",SUMIFS($C$6:$C$60,$B$6:$B$60,B15)) | F15: =IF(B15="","",IF(COUNTIFS(Assets!$A$6:$A$25,B15)=0,"asset not on Assets",IF(E15>100,"asset over 100% across groups (register H7)","OK")))
D16: =IF(A16="","",IFERROR(INDEX(Groups!$B$6:$B$15,MATCH(A16,Groups!$A$6:$A$15,0)),"UNKNOWN GROUP")) | E16: =IF(B16="","",SUMIFS($C$6:$C$60,$B$6:$B$60,B16)) | F16: =IF(B16="","",IF(COUNTIFS(Assets!$A$6:$A$25,B16)=0,"asset not on Assets",IF(E16>100,"asset over 100% across groups (register H7)","OK")))
D17: =IF(A17="","",IFERROR(INDEX(Groups!$B$6:$B$15,MATCH(A17,Groups!$A$6:$A$15,0)),"UNKNOWN GROUP")) | E17: =IF(B17="","",SUMIFS($C$6:$C$60,$B$6:$B$60,B17)) | F17: =IF(B17="","",IF(COUNTIFS(Assets!$A$6:$A$25,B17)=0,"asset not on Assets",IF(E17>100,"asset over 100% across groups (register H7)","OK")))
D18: =IF(A18="","",IFERROR(INDEX(Groups!$B$6:$B$15,MATCH(A18,Groups!$A$6:$A$15,0)),"UNKNOWN GROUP")) | E18: =IF(B18="","",SUMIFS($C$6:$C$60,$B$6:$B$60,B18)) | F18: =IF(B18="","",IF(COUNTIFS(Assets!$A$6:$A$25,B18)=0,"asset not on Assets",IF(E18>100,"asset over 100% across groups (register H7)","OK")))
D19: =IF(A19="","",IFERROR(INDEX(Groups!$B$6:$B$15,MATCH(A19,Groups!$A$6:$A$15,0)),"UNKNOWN GROUP")) | E19: =IF(B19="","",SUMIFS($C$6:$C$60,$B$6:$B$60,B19)) | F19: =IF(B19="","",IF(COUNTIFS(Assets!$A$6:$A$25,B19)=0,"asset not on Assets",IF(E19>100,"asset over 100% across groups (register H7)","OK")))
D20: =IF(A20="","",IFERROR(INDEX(Groups!$B$6:$B$15,MATCH(A20,Groups!$A$6:$A$15,0)),"UNKNOWN GROUP")) | E20: =IF(B20="","",SUMIFS($C$6:$C$60,$B$6:$B$60,B20)) | F20: =IF(B20="","",IF(COUNTIFS(Assets!$A$6:$A$25,B20)=0,"asset not on Assets",IF(E20>100,"asset over 100% across groups (register H7)","OK")))
D21: =IF(A21="","",IFERROR(INDEX(Groups!$B$6:$B$15,MATCH(A21,Groups!$A$6:$A$15,0)),"UNKNOWN GROUP")) | E21: =IF(B21="","",SUMIFS($C$6:$C$60,$B$6:$B$60,B21)) | F21: =IF(B21="","",IF(COUNTIFS(Assets!$A$6:$A$25,B21)=0,"asset not on Assets",IF(E21>100,"asset over 100% across groups (register H7)","OK")))
... D60: =IF(A60="","",IFERROR(INDEX(Groups!$B$6:$B$15,MATCH(A60,Groups!$A$6:$A$15,0)),"UNKNOWN GROUP")) | E60: =IF(B60="","",SUMIFS($C$6:$C$60,$B$6:$B$60,B60)) | F60: =IF(B60="","",IF(COUNTIFS(Assets!$A$6:$A$25,B60)=0,"asset not on Assets",IF(E60>100,"asset over 100% across groups (register H7)","OK")))

Sheet Rate_Builder
A1: Rate Builder calculators (one row per line)
A2: qs_tools_rate_builder_calculators_v1. Rows with the same Calculator Ref form one calculator. A linked Asset Ref makes it per-asset (Path B).
A4: Calculator Ref | B4: Linked Group Ref | C4: Linked Asset Ref (blank = group calculator) | D4: Line label | E4: Unit | F4: Rate ($) | G4: Quantity | H4: Output driver (Y/N) | I4: Line value (check) | J4: Notes
A5: EXAMPLE | B5: G01 | C5: A01 | D5: Machine hire | E5: hr | F5: 120 | G5: 1 | H5: Y | I5: 120 | J5: Example only - skipped
A6: C01 | B6: G01 | C6: A01 | D6: Machine hire | E6: hr | G6: 1 | H6: Y | I6: =IF(OR(F6="",G6=""),0,F6*G6) -> 0
A7: C02 | B7: G01 | C7: A02 | D7: Machine hire | E7: hr | G7: 1 | H7: Y | I7: =IF(OR(F7="",G7=""),0,F7*G7) -> 0
A8: C03 | B8: G02 | C8: A03 | D8: Machine hire | E8: hr | G8: 1 | H8: Y | I8: =IF(OR(F8="",G8=""),0,F8*G8) -> 0
A9: C04 | B9: G02 | C9: A04 | D9: Machine hire | E9: hr | G9: 1 | H9: Y | I9: =IF(OR(F9="",G9=""),0,F9*G9) -> 0
I10: =IF(OR(F10="",G10=""),0,F10*G10) -> 0
I11: =IF(OR(F11="",G11=""),0,F11*G11) -> 0
I12: =IF(OR(F12="",G12=""),0,F12*G12) -> 0
I13: =IF(OR(F13="",G13=""),0,F13*G13) -> 0
I14: =IF(OR(F14="",G14=""),0,F14*G14) -> 0
I15: =IF(OR(F15="",G15=""),0,F15*G15) -> 0
I16: =IF(OR(F16="",G16=""),0,F16*G16) -> 0
I17: =IF(OR(F17="",G17=""),0,F17*G17) -> 0
I18: =IF(OR(F18="",G18=""),0,F18*G18) -> 0
I19: =IF(OR(F19="",G19=""),0,F19*G19) -> 0
I20: =IF(OR(F20="",G20=""),0,F20*G20) -> 0
I21: =IF(OR(F21="",G21=""),0,F21*G21) -> 0
... I45: =IF(OR(F45="",G45=""),0,F45*G45) -> 0
A47: Machine calculators price the MACHINE only (Stage 1b). Labour is charged from Charge_Out, not from these lines.

Sheet PnL
A1: P&L inputs (annual, excl GST)
A2: qs_tools_profit_and_loss_state. Labour lines and asset interest are DERIVED by the generator from Staff and Assets - do not enter them here.
A4: Line label | B4: Section | C4: Category | D4: Sub-category / direct cost category | E4: Amount ($/yr) | F4: Notes
A5: EXAMPLE | B5: operating_expenses | C5: general_overheads | D5: facilities_premises | E5: 24000 | F5: Example only - skipped
A6: Sales | B6: trading_income | C6: revenue | F6: Revenue. Drives the P&L reconciliation.
A7: Materials | B7: cost_of_sales | C7: cogs | D7: materials | F7: Direct cost
A8: Rent | B8: operating_expenses | C8: general_overheads | D8: facilities_premises
A9: Insurance | B9: operating_expenses | C9: general_overheads | D9: insurance_compliance
A10: Accounting fees | B10: operating_expenses | C10: general_overheads | D10: finance_admin
A11: Software subscriptions | B11: operating_expenses | C11: general_overheads | D11: office_admin
A12: Phone and internet | B12: operating_expenses | C12: general_overheads | D12: office_admin
A13: Marketing | B13: operating_expenses | C13: general_overheads | D13: sales_growth
A14: Staff expenses | B14: operating_expenses | C14: general_overheads | D14: staff_overheads
A15: Vehicle fuel | B15: operating_expenses | C15: general_overheads | D15: vehicle_running_costs | F15: Avoid the words 'asset finance' in labels (S1 trap)
A32: Revenue | E32: =SUMIFS(E6:E30,C6:C30,"revenue") -> 0
A33: Direct costs (COGS) | E33: =SUMIFS(E6:E30,C6:C30,"cogs") -> 0
A34: General overheads entered | E34: =SUMIFS(E6:E30,C6:C30,"general_overheads") -> 0
A35: Base wages from Staff (check only - the generator adds leave, KiwiSaver and ACC) | E35: =Staff!T32 -> 0
A36: Rough margin before labour on-costs and asset finance (check) | E36: =E32-E33-E34-E35 -> 0
A38: Sub-category values for overheads come from the app's P&L review list; the generator maps each to the matching General Overheads category.

Sheet Checks
A1: Checks
A2: Every flag should read OK before the template is handed to the generator.
A4: Check | B4: Value | C4: Expected / rule | D4: Flag
A5: Total headcount | B5: =Staff!D32 -> 10 | C5: Scenario A: 10
A6: Productive headcount | B6: =SUMIFS(Staff!D6:D30,Staff!E6:E30,"productive") -> 7 | C6: Scenario A: 7
A7: Non-productive headcount | B7: =SUMIFS(Staff!D6:D30,Staff!E6:E30,"non_productive") -> 3 | C7: Scenario A: 3
A8: Productive assets | B8: =SUMIFS(Assets!C6:C25,Assets!D6:D25,"productive") -> 4 | C8: Scenario A: 4
A9: Support assets | B9: =SUMIFS(Assets!C6:C25,Assets!D6:D25,"support") -> 3 | C9: Scenario A: 3
A10: Staff rows missing a labour rate | B10: =COUNTIFS(Staff!B6:B30,"<>",Staff!I6:I30,"") -> 6 | C10: 0 | D10: =IF(B10=0,"OK","FILL IN") -> FILL IN
A11: Productive types missing a charge-out rate | B11: =COUNTIF(Charge_Out!F5:F14,"MISSING*") -> 3 | C11: 0 | D11: =IF(B11=0,"OK","FILL IN") -> FILL IN
A12: Productive assets missing a purchase price | B12: =COUNTIFS(Assets!D6:D25,"productive",Assets!H6:H25,"") -> 4 | C12: 0 (enter 0 if owned outright) | D12: =IF(B12=0,"OK","FILL IN") -> FILL IN
A13: Labour assignment rows with a problem | B13: =COUNTIFS(Labour_Assign!F6:F60,"<>OK",Labour_Assign!B6:B60,"<>") -> 9 | C13: 0 | D13: =IF(B13=0,"OK","REVIEW") -> REVIEW
A14: Asset assignment rows with a problem | B14: =COUNTIFS(Asset_Assign!F6:F60,"<>OK",Asset_Assign!B6:B60,"<>") -> 0 | C14: 0 | D14: =IF(B14=0,"OK","REVIEW") -> OK
A15: Groups with a problem | B15: =COUNTIFS(Groups!H6:H15,"<>OK",Groups!B6:B15,"<>") -> 4 | C15: 0 | D15: =IF(B15=0,"OK","REVIEW") -> REVIEW
A16: Productive assets with no Rate Builder line | B16: =SUMPRODUCT((Assets!D6:D25="productive")*(COUNTIF(Rate_Builder!C6:C45,Assets!A6:A25)=0)) -> 0 | C16: 0 (otherwise 'Not priced', E-2) | D16: =IF(B16=0,"OK","REVIEW") -> OK
A17: Rate Builder lines with no rate | B17: =COUNTIFS(Rate_Builder!A6:A45,"<>",Rate_Builder!F6:F45,"") -> 4 | C17: 0 | D17: =IF(B17=0,"OK","FILL IN") -> FILL IN
A18: Revenue entered | B18: =PnL!E32 -> 0 | C18: > 0 | D18: =IF(B18>0,"OK","FILL IN") -> FILL IN
A19: Owner labour treatment chosen | B19: =IF(Business!B11="","",Business!B11) | C19: pick one (Q-1) | D19: =IF(B19="","FILL IN","OK") -> FILL IN
A20: Materials markup entered | B20: =Business!B9 -> 0 | C20: whole number | D20: =IF(B20="","FILL IN","OK") -> FILL IN

Sheet Lists
A1: staff_type_id | B1: staff_type_name (system type, app label) | C1: labour_class | D1: yes_no | E1: asset_type | F1: recovery_hour_source | G1: asset_run_pattern | H1: overhead_subcategory | I1: direct_cost_category | J1: non_productive_policy | K1: owner_labour_treatment | L1: unit
A2: owner_director | B2: Owner / Director | C2: productive | D2: Y | E2: productive | F2: asset_hours | G2: together | H2: facilities_premises | I2: materials | J2: charge_to_self | K2: owner_on_wages_in_pnl | L2: hr
A3: manager | B3: Manager | C3: non_productive | D3: N | E3: support | F3: labour_hours | G3: sequential | H3: finance_admin | I3: subcontract_labour | J3: spread_as_overhead | K3: owner_paid_by_drawings_not_in_pnl | L3: day
A4: supervisor_team_lead | B4: Supervisor / Team Lead | H4: insurance_compliance | I4: subcontracting_general | L4: each
A5: senior_operator_staff | B5: Senior Operator / Senior Staff | H5: office_admin | I5: hired_equipment_plant | L5: m3
A6: operator_delivery_staff | B6: Operator / Delivery Staff | H6: sales_growth | I6: freight_cartage | L6: m2
A7: junior_trainee | B7: Junior / Trainee | H7: staff_overheads | I7: waste_tipping | L7: km
A8: admin_support | B8: Administration / Support | H8: travel | I8: direct_consumables
A9: sales_customer_support | B9: Sales / Customer Support | H9: vehicle_running_costs | I9: other_direct_costs
A10: finance_accounts | B10: Finance / Accounts | H10: finance_interest
A11: other_review_required | B11: Other / Review required
A14: Lists used by the dropdowns. Values are the exact strings the app stores - do not edit.
